udpipe_parser_temp/__init__.py
udpipe_parser_temp/dicts.py
udpipe_parser_temp/parser_tester.py
udpipe_parser_temp/text_preprocessor.py
udpipe_parser_temp/udpipe_parser_temp.py
udpipe_parser_temp/utilities.py
udpipe_parser_temp-0.9.4.dist-info/METADATA
udpipe_parser_temp-0.9.4.dist-info/WHEEL
udpipe_parser_temp-0.9.4.dist-info/top_level.txt
udpipe_parser_temp-0.9.4.dist-info/RECORD
